{
    "tables": [
        {
            "id": "8f76d930-0f81-11ea-a81e-a908a8640844",
            "title": "dwadaswad",
            "cardIds": ["897c9b20-11e1-11ea-832b-2f338aea652b"]
        },
        {
            "id": "2a492b70-105e-11ea-b016-77a86307ab9f",
            "title": "dwd",
            "cardIds": []
        },
        {
            "id": "00d58d10-11cb-11ea-81ac-95c0278a25a3",
            "title": "New table",
            "cardIds": []
        }
    ],
    "cards": [
        {
            "done": false,
            "executor": "",
            "desc": "",
            "id": "897c9b20-11e1-11ea-832b-2f338aea652b",
            "text": "dwad",
            "tableId": "8f76d930-0f81-11ea-a81e-a908a8640844"
        }
    ],
    "order": {
        "order": [
            "8f76d930-0f81-11ea-a81e-a908a8640844",
            "2a492b70-105e-11ea-b016-77a86307ab9f",
            "00d58d10-11cb-11ea-81ac-95c0278a25a3"
        ]
    },
    "executors": [
        {
            "id": "00",
            "name": "John Doe"
        },
        {
            "id": "01",
            "name": "Benedict Cumberbatch"
        },
        {
            "id": "02",
            "name": "Benedryl Cabbagepatch"
        },
        {
            "id": "03",
            "name": "Bendycat Hairysnatch"
        },
        {
            "id": "04",
            "name": "Bandicoot Bandersnatch"
        }
    ]
}
